computeclient/computeclient.py
vmstate/vmstate.py
vmstate-1.4.dist-info/METADATA
vmstate-1.4.dist-info/WHEEL
vmstate-1.4.dist-info/top_level.txt
vmstate-1.4.dist-info/RECORD
